bbtaskworker/__init__.py
bbtaskworker-0.0.1.dist-info/METADATA
bbtaskworker-0.0.1.dist-info/WHEEL
bbtaskworker-0.0.1.dist-info/top_level.txt
bbtaskworker-0.0.1.dist-info/RECORD
