Metadata-Version: 2.1
Name: bbtaskworker
Version: 0.0.1
Summary: bbtaskworker
Home-page: https://github.com/schrodinger/
Author: Andy Martin
Author-email: andy.martin@schrodinger.com
License: UNKNOWN
Platform: UNKNOWN
